[{"name":"🩵 𝙁𝙡𝙤𝙬 𝙞𝙣𝙨𝙖𝙣𝙤 🩵","groupId":"120363404321083096@g.us","x9":false,"antiimg":false,"antistatus":false,"antivideo":false,"antiaudio":false,"antisticker":false,"antidoc":false,"antictt":true,"antiloc":false,"antilinkgp":true,"antilinkhard":true,"antilinkeasy":true,"antifake":false,"antiporn":false,"Odelete":false,"antispam":false,"antinotas":false,"anticatalogo":true,"visuUnica":false,"registrarFIGUS":false,"soadm":false,"listanegra":[],"advertir":[],"prefixos":["."],"advertir2":[],"legenda_estrangeiro":"0","legenda_documento":"0","legenda_video":"0","legenda_imagem":"0","multiprefix":false,"ausentes":[],"ANTI_DDD":{"active":false,"listaProibidos":[]},"antipalavrao":{"active":false,"palavras":[]},"limitec":{"active":false,"quantidade":null},"wellcome":[{"bemvindo1":false,"legendabv":"✨ 𝙾𝙻𝙰 #numerodele# 𝚂𝙴𝙹𝙰 𝙱𝙴𝙼 𝚅𝙸𝙽𝙳𝙾[ 𝙰 ] 𝙰𝙾 𝙶𝚁𝚄𝙿𝙾 #nomedogp#\n\n• 𝙻𝙴𝙸𝙰 𝙰𝚂 𝚁𝙴𝙶𝚁𝙰𝚂 𝙴 𝙰𝙿𝚁𝙾𝚅𝙴𝙸𝚃𝙴 𝙾 𝙶𝚁𝚄𝙿𝙾\n> 𝐫𝐮𝐚𝐧 𝐛𝐨𝐭","legendasaiu":0,"fundobv":null},{"bemvindo2":false,"legendabv2":"✨ 𝙾𝙻𝙰 #numerodele# 𝚂𝙴𝙹𝙰 𝙱𝙴𝙼 𝚅𝙸𝙽𝙳𝙾[ 𝙰 ] 𝙰𝙾 𝙶𝚁𝚄𝙿𝙾   #nomedogp#\n\n• 𝙻𝙴𝙸𝙰 𝙰𝚂 𝚁𝙴𝙶𝚁𝙰𝚂 𝙴 𝙰𝙿𝚁𝙾𝚅𝙴𝙸𝚃𝙴 𝙾 𝙶𝚁𝚄𝙿𝙾\n> 𝐫𝐮𝐚𝐧 𝐛𝐨𝐭","legendasaiu2":0}],"autosticker":false,"autoresposta":true,"jogos":true,"bangp":false,"modo_rpg":false,"antilink":true,"antiroubo":true,"ar_permitidos":["559984653570","5511991356821"],"ar_permitidos_lid":["7100252033253","98630400770159"]}]